pytest_docker_fixtures/__init__.py
pytest_docker_fixtures/images.py
pytest_docker_fixtures/containers/__init__.py
pytest_docker_fixtures/containers/_base.py
pytest_docker_fixtures/containers/cockroach.py
pytest_docker_fixtures/containers/emqx.py
pytest_docker_fixtures/containers/es.py
pytest_docker_fixtures/containers/etcd.py
pytest_docker_fixtures/containers/influxdb.py
pytest_docker_fixtures/containers/kafka.py
pytest_docker_fixtures/containers/memcached.py
pytest_docker_fixtures/containers/minio.py
pytest_docker_fixtures/containers/mysql.py
pytest_docker_fixtures/containers/pg.py
pytest_docker_fixtures/containers/rabbitmq.py
pytest_docker_fixtures/containers/redis.py
pytest_docker_fixtures/containers/stripe.py
pytest_docker_fixtures/containers/valkey.py
pytest_docker_fixtures-1.4.0.dist-info/METADATA
pytest_docker_fixtures-1.4.0.dist-info/WHEEL
pytest_docker_fixtures-1.4.0.dist-info/top_level.txt
pytest_docker_fixtures-1.4.0.dist-info/zip-safe
pytest_docker_fixtures-1.4.0.dist-info/RECORD
