Metadata-Version: 2.1
Name: pytest-docker-fixtures
Version: 1.4.0
Summary: pytest docker fixtures
Home-page: https://github.com/guillotinaweb/pytest-docker-fixtures
Author: Nathan Van Gheem
Author-email: vangheem@gmail.com
License: BSD
Keywords: pytest,fixtures,docker
Classifier: License :: OSI Approved :: BSD License
Classifier: Development Status :: 3 - Alpha
Classifier: Intended Audience :: Developers
Classifier: Programming Language :: Python :: 3.6
Classifier: Topic :: Software Development :: Libraries :: Python Modules
Requires-Dist: pytest
Requires-Dist: docker
Requires-Dist: requests
Provides-Extra: kafka
Requires-Dist: kafka-python; extra == "kafka"
Provides-Extra: memcached
Requires-Dist: pymemcache; extra == "memcached"
Provides-Extra: mysql
Requires-Dist: mysql-connector-python~=8.0.17; extra == "mysql"
Provides-Extra: pg
Requires-Dist: psycopg2-binary; extra == "pg"
Provides-Extra: rabbitmq
Requires-Dist: pika==0.12.0; extra == "rabbitmq"
